[
	{
		"inputs": [],
		"name": "claimReward",
		"outputs": [],
		"stateMutability": "nonpayable",
		"type": "function"
	},
	{
		"inputs": [
			{
				"internalType": "uint256",
				"name": "amount",
				"type": "uint256"
			}
		],
		"name": "stake",
		"outputs": [],
		"stateMutability": "nonpayable",
		"type": "function"
	},
	{
		"inputs": [
			{
				"internalType": "address",
				"name": "_token",
				"type": "address"
			},
			{
				"internalType": "address",
				"name": "_feeRecipient",
				"type": "address"
			},
			{
				"internalType": "uint256",
				"name": "_minimumStakeTime",
				"type": "uint256"
			},
			{
				"internalType": "uint256",
				"name": "_rewardApr",
				"type": "uint256"
			}
		],
		"stateMutability": "nonpayable",
		"type": "constructor"
	},
	{
		"inputs": [
			{
				"internalType": "uint256",
				"name": "amount",
				"type": "uint256"
			}
		],
		"name": "withdraw",
		"outputs": [],
		"stateMutability": "nonpayable",
		"type": "function"
	},
	{
		"inputs": [
			{
				"internalType": "uint256",
				"name": "amount",
				"type": "uint256"
			}
		],
		"name": "withdrawTest",
		"outputs": [],
		"stateMutability": "nonpayable",
		"type": "function"
	},
	{
		"inputs": [],
		"name": "feeRecipent",
		"outputs": [
			{
				"internalType": "address",
				"name": "",
				"type": "address"
			}
		],
		"stateMutability": "view",
		"type": "function"
	},
	{
		"inputs": [
			{
				"internalType": "address",
				"name": "user",
				"type": "address"
			}
		],
		"name": "getUser",
		"outputs": [
			{
				"internalType": "uint256",
				"name": "balance",
				"type": "uint256"
			},
			{
				"internalType": "uint256",
				"name": "reward",
				"type": "uint256"
			}
		],
		"stateMutability": "view",
		"type": "function"
	},
	{
		"inputs": [
			{
				"internalType": "address",
				"name": "user",
				"type": "address"
			}
		],
		"name": "getUserTest",
		"outputs": [
			{
				"internalType": "uint256",
				"name": "balance",
				"type": "uint256"
			},
			{
				"internalType": "uint256",
				"name": "reward",
				"type": "uint256"
			}
		],
		"stateMutability": "view",
		"type": "function"
	},
	{
		"inputs": [],
		"name": "minimumStakeTime",
		"outputs": [
			{
				"internalType": "uint256",
				"name": "",
				"type": "uint256"
			}
		],
		"stateMutability": "view",
		"type": "function"
	},
	{
		"inputs": [],
		"name": "rewardApr",
		"outputs": [
			{
				"internalType": "uint256",
				"name": "",
				"type": "uint256"
			}
		],
		"stateMutability": "view",
		"type": "function"
	},
	{
		"inputs": [],
		"name": "token",
		"outputs": [
			{
				"internalType": "contract P2PToken",
				"name": "",
				"type": "address"
			}
		],
		"stateMutability": "view",
		"type": "function"
	},
	{
		"inputs": [
			{
				"internalType": "address",
				"name": "",
				"type": "address"
			}
		],
		"name": "userStake",
		"outputs": [
			{
				"internalType": "uint256",
				"name": "balance",
				"type": "uint256"
			},
			{
				"internalType": "uint256",
				"name": "lastUpdateTime",
				"type": "uint256"
			},
			{
				"internalType": "uint256",
				"name": "lastStakeTime",
				"type": "uint256"
			}
		],
		"stateMutability": "view",
		"type": "function"
	}
]